Metadata-Version: 1.0
Name: yacht-scraper
Version: 0.0.6
Summary: Package that allows scraping of yacht data from boat24.com
Home-page: https://github.com/nishaalajmera/Yacht_scraper.git
Author: Nishaal Ajmera
Author-email: UNKNOWN
License: MIT
Platform: UNKNOWN
